<?xml version="1.0" encoding="UTF-8"?>
<beans xmlns="http://www.springframework.org/schema/beans"
	xmlns:xsi="http://www.w3.org/2001/XMLSchema-instance" xmlns:aop="http://www.springframework.org/schema/aop"
	xsi:schemaLocation="
			http://www.springframework.org/schema/beans http://www.springframework.org/schema/beans/spring-beans-2.5.xsd
			http://www.springframework.org/schema/aop http://www.springframework.org/schema/aop/spring-aop-2.5.xsd">

	<description>
		To be used for transaction controller and transaction
		operation.
		Transaction operation will have the property to set bus
		manager, which
		get from 'AppContext_Services.xml'
    </description>

	<bean id="ReadPartyGroupOperation"
		class="com.integrosys.cms.app.partygroup.trx.ReadPartyGroupOperation">
		<property name="partyGroupBusManager" ref="partyGroupBusManager" />
		<property name="stagingPartyGroupBusManager" ref="stagingPartyGroupBusManager" />
	</bean>
	<bean id="MakerCreateSavedPartyGroupOperation"
		class="com.integrosys.cms.app.partygroup.trx.MakerCreateSavedPartyGroupOperation">
		<property name="partyGroupBusManager" ref="partyGroupBusManager" />
		<property name="stagingPartyGroupBusManager" ref="stagingPartyGroupBusManager" />
	</bean>

	<bean id="MakerCloseRejectedCreatePartyGroupOperation"
		class="com.integrosys.cms.app.partygroup.trx.MakerCloseRejectedCreatePartyGroupOperation">
		<property name="partyGroupBusManager" ref="partyGroupBusManager" />
		<property name="stagingPartyGroupBusManager" ref="stagingPartyGroupBusManager" />
	</bean>

	<bean id="MakerSaveUpdatePartyGroupOperation"
		class="com.integrosys.cms.app.partygroup.trx.MakerSaveUpdatePartyGroupOperation">
		<property name="partyGroupBusManager" ref="partyGroupBusManager" />
		<property name="stagingPartyGroupBusManager" ref="stagingPartyGroupBusManager" />
	</bean>
	<bean id="MakerSavePartyGroupOperation"
		class="com.integrosys.cms.app.partygroup.trx.MakerSavePartyGroupOperation">
		<property name="partyGroupBusManager" ref="partyGroupBusManager" />
		<property name="stagingPartyGroupBusManager" ref="stagingPartyGroupBusManager" />
	</bean>

	<bean id="ReadPartyGroupIDOperation"
		class="com.integrosys.cms.app.partygroup.trx.ReadPartyGroupIDOperation">
		<property name="partyGroupBusManager" ref="partyGroupBusManager" />
		<property name="stagingPartyGroupBusManager" ref="stagingPartyGroupBusManager" />
	</bean>
	<bean id="MakerUpdatePartyGroupOperation"
		class="com.integrosys.cms.app.partygroup.trx.MakerUpdatePartyGroupOperation">
		<property name="partyGroupBusManager" ref="partyGroupBusManager" />
		<property name="stagingPartyGroupBusManager" ref="stagingPartyGroupBusManager" />
	</bean>
	<bean id="MakerEditRejectedDeletePartyGroupOperation"
		class="com.integrosys.cms.app.partygroup.trx.MakerEditRejectedDeletePartyGroupOperation">
		<property name="partyGroupBusManager" ref="partyGroupBusManager" />
		<property name="stagingPartyGroupBusManager" ref="stagingPartyGroupBusManager" />
	</bean>
	<bean id="MakerActivatePartyGroupOperation"
		class="com.integrosys.cms.app.partygroup.trx.MakerActivatePartyGroupOperation">
		<property name="partyGroupBusManager" ref="partyGroupBusManager" />
		<property name="stagingPartyGroupBusManager" ref="stagingPartyGroupBusManager" />
	</bean>

	<bean id="MakerEditRejectedUpdatePartyGroupOperation"
		class="com.integrosys.cms.app.partygroup.trx.MakerEditRejectedUpdatePartyGroupOperation">
		<property name="partyGroupBusManager" ref="partyGroupBusManager" />
		<property name="stagingPartyGroupBusManager" ref="stagingPartyGroupBusManager" />
	</bean>
	<bean id="MakerCloseRejectedUpdatePartyGroupOperation"
		class="com.integrosys.cms.app.partygroup.trx.MakerCloseRejectedUpdatePartyGroupOperation">
		<property name="partyGroupBusManager" ref="partyGroupBusManager" />
		<property name="stagingPartyGroupBusManager" ref="stagingPartyGroupBusManager" />
	</bean>
	<bean id="MakerCloseDraftPartyGroupOperation"
		class="com.integrosys.cms.app.partygroup.trx.MakerCloseDraftPartyGroupOperation">
		<property name="partyGroupBusManager" ref="partyGroupBusManager" />
		<property name="stagingPartyGroupBusManager" ref="stagingPartyGroupBusManager" />
	</bean>
	<bean id="CheckerApproveUpdatePartyGroupOperation"
		class="com.integrosys.cms.app.partygroup.trx.CheckerApproveUpdatePartyGroupOperation">
		<property name="partyGroupBusManager" ref="partyGroupBusManager" />
		<property name="stagingPartyGroupBusManager" ref="stagingPartyGroupBusManager" />
	</bean>
	<bean id="CheckerApproveDeletePartyGroupOperation"
		class="com.integrosys.cms.app.partygroup.trx.CheckerApproveDeletePartyGroupOperation">
		<property name="partyGroupBusManager" ref="partyGroupBusManager" />
		<property name="stagingPartyGroupBusManager" ref="stagingPartyGroupBusManager" />
	</bean>
	<bean id="CheckerApproveCreatePartyGroupOperation"
		class="com.integrosys.cms.app.partygroup.trx.CheckerApproveCreatePartyGroupOperation">
		<property name="partyGroupBusManager" ref="partyGroupBusManager" />
		<property name="stagingPartyGroupBusManager" ref="stagingPartyGroupBusManager" />
	</bean>
	<bean id="CheckerRejectPartyGroupOperation"
		class="com.integrosys.cms.app.partygroup.trx.CheckerRejectPartyGroupOperation">
		<property name="partyGroupBusManager" ref="partyGroupBusManager" />
		<property name="stagingPartyGroupBusManager" ref="stagingPartyGroupBusManager" />
	</bean>
	<bean id="MakerEditRejectedCreatePartyGroupOperation"
		class="com.integrosys.cms.app.partygroup.trx.MakerEditRejectedCreatePartyGroupOperation">
		<property name="partyGroupBusManager" ref="partyGroupBusManager" />
		<property name="stagingPartyGroupBusManager" ref="stagingPartyGroupBusManager" />
	</bean>
	<bean id="MakerCloseRejectedDisablePartyGroupOperation"
		class="com.integrosys.cms.app.partygroup.trx.MakerCloseRejectedDisablePartyGroupOperation">
		<property name="partyGroupBusManager" ref="partyGroupBusManager" />
		<property name="stagingPartyGroupBusManager" ref="stagingPartyGroupBusManager" />
	</bean>
	<bean id="MakerEditRejectedEnablePartyGroupOperation"
		class="com.integrosys.cms.app.partygroup.trx.MakerEditRejectedEnablePartyGroupOperation">
		<property name="partyGroupBusManager" ref="partyGroupBusManager" />
		<property name="stagingPartyGroupBusManager" ref="stagingPartyGroupBusManager" />
	</bean>

	<bean id="CheckerRejectActivatePartyGroupOperation"
		class="com.integrosys.cms.app.partygroup.trx.CheckerRejectActivatePartyGroupOperation">
		<property name="partyGroupBusManager" ref="partyGroupBusManager" />
		<property name="stagingPartyGroupBusManager" ref="stagingPartyGroupBusManager" />
	</bean>

	<bean id="CheckerApproveEnablePartyGroupOperation"
		class="com.integrosys.cms.app.partygroup.trx.CheckerApproveEnablePartyGroupOperation">
		<property name="partyGroupBusManager" ref="partyGroupBusManager" />
		<property name="stagingPartyGroupBusManager" ref="stagingPartyGroupBusManager" />
	</bean>

	<bean id="MakerDeletePartyGroupOperation"
		class="com.integrosys.cms.app.partygroup.trx.MakerDeletePartyGroupOperation">
		<property name="partyGroupBusManager" ref="partyGroupBusManager" />
		<property name="stagingPartyGroupBusManager" ref="stagingPartyGroupBusManager" />
	</bean>


	<bean id="MakerCreatePartyGroupOperation"
		class="com.integrosys.cms.app.partygroup.trx.MakerCreatePartyGroupOperation">
		<property name="partyGroupBusManager" ref="partyGroupBusManager" />
		<property name="stagingPartyGroupBusManager" ref="stagingPartyGroupBusManager" />
	</bean>
	<bean id="partyGroupReadController"
		class="com.integrosys.cms.app.partygroup.trx.PartyGroupReadController">
		<property name="nameTrxOperationMap">
			<map>
				<entry key="ReadPartyGroupOperation" value-ref="ReadPartyGroupOperation" />
				<entry key="ReadPartyGroupIDOperation" value-ref="ReadPartyGroupIDOperation" />


			</map>
		</property>
	</bean>

	<bean id="partyGroupTrxController"
		class="com.integrosys.cms.app.partygroup.trx.PartyGroupTrxController">
		<property name="nameTrxOperationMap">
			<map>
				<entry key="MakerEditRejectedUpdatePartyGroupOperation"
					value-ref="MakerEditRejectedUpdatePartyGroupOperation" />
				<entry key="MakerUpdatePartyGroupOperation" value-ref="MakerUpdatePartyGroupOperation" />
				<entry key="MakerSaveUpdatePartyGroupOperation" value-ref="MakerSaveUpdatePartyGroupOperation" />
				<entry key="MakerCloseDraftPartyGroupOperation" value-ref="MakerCloseDraftPartyGroupOperation" />
				<entry key="MakerCloseRejectedUpdatePartyGroupOperation"
					value-ref="MakerCloseRejectedUpdatePartyGroupOperation" />
				<entry key="CheckerApproveUpdatePartyGroupOperation"
					value-ref="CheckerApproveUpdatePartyGroupOperation" />
				<entry key="CheckerApproveCreatePartyGroupOperation"
					value-ref="CheckerApproveCreatePartyGroupOperation" />
				<entry key="CheckerRejectPartyGroupOperation" value-ref="CheckerRejectPartyGroupOperation" />
				<entry key="MakerCreatePartyGroupOperation" value-ref="MakerCreatePartyGroupOperation" />
				<entry key="MakerEditRejectedCreatePartyGroupOperation"
					value-ref="MakerEditRejectedCreatePartyGroupOperation" />
				<entry key="MakerDeletePartyGroupOperation" value-ref="MakerDeletePartyGroupOperation" />
				<entry key="CheckerApproveUpdatePartyGroupOperation"
					value-ref="CheckerApproveUpdatePartyGroupOperation" />
				<entry key="CheckerRejectPartyGroupOperation" value-ref="CheckerRejectPartyGroupOperation" />
				<entry key="CheckerApproveDeletePartyGroupOperation"
					value-ref="CheckerApproveDeletePartyGroupOperation" />
				<entry key="MakerActivatePartyGroupOperation" value-ref="MakerActivatePartyGroupOperation" />
				<entry key="CheckerApproveEnablePartyGroupOperation"
					value-ref="CheckerApproveEnablePartyGroupOperation" />
				<entry key="MakerSavePartyGroupOperation" value-ref="MakerSavePartyGroupOperation" />
				<entry key="MakerEditRejectedDeletePartyGroupOperation"
					value-ref="MakerEditRejectedDeletePartyGroupOperation" />
				<entry key="CheckerRejectActivatePartyGroupOperation"
					value-ref="CheckerRejectActivatePartyGroupOperation" />
				<entry key="MakerCloseRejectedDisablePartyGroupOperation"
					value-ref="MakerCloseRejectedDisablePartyGroupOperation" />
				<entry key="MakerEditRejectedEnablePartyGroupOperation"
					value-ref="MakerEditRejectedEnablePartyGroupOperation" />
				<entry key="MakerCloseRejectedCreatePartyGroupOperation"
					value-ref="MakerCloseRejectedCreatePartyGroupOperation" />
				<entry key="MakerCreateSavedPartyGroupOperation" value-ref="MakerCreateSavedPartyGroupOperation" />

			</map>
		</property>
		<property name="processTrxManager" ref="processTrxManager" />
	</bean>

	<bean id="partyGroupTrxControllerFactory"
		class="com.integrosys.cms.app.partygroup.trx.PartyGroupTrxControllerFactory">
		<property name="partyGroupReadController" ref="partyGroupReadController" />
		<property name="partyGroupTrxController" ref="partyGroupTrxController" />
	</bean>
</beans>